{"status":"success","data":{"year":"2025","period":"all","saluran_pengaduan":[{"kode":"APE","nama":"STPP","jumlah":61},{"kode":"ULP","nama":"Permintaan Informasi/Konsultasi/Pengaduan","jumlah":0},{"kode":"UPG","nama":"Laporan ke UPG","jumlah":0},{"kode":"LNK","nama":"Link G-Form","jumlah":0},{"kode":"WHA","nama":"WA (WhatsApp)","jumlah":0},{"kode":"KOT","nama":"Kotak Saran","jumlah":0},{"kode":"MED","nama":"Media Sosial","jumlah":0}],"klasifikasi_pengaduan":[{"no":1,"kode":"SKM1","nama":"Kesesuaian persyaratan pelayanan","jumlah":4},{"no":2,"kode":"SKM2","nama":"Kemudahan prosedur","jumlah":6},{"no":3,"kode":"SKM3","nama":"Kecepatan pelayanan","jumlah":4},{"no":4,"kode":"SKM4","nama":"Biaya/tarif pelayanan","jumlah":9},{"no":5,"kode":"SKM5","nama":"Kesesuaian produk","jumlah":10},{"no":6,"kode":"SKM6","nama":"Perilaku petugas","jumlah":6},{"no":7,"kode":"SKM7","nama":"Kompetensi/kemampuan petugas","jumlah":7},{"no":8,"kode":"SKM8","nama":"Penanganan pengaduan","jumlah":7},{"no":9,"kode":"SKM9","nama":"Kualitas sarana dan prasarana","jumlah":8},{"no":10,"kode":"GRA","nama":"Gratifikasi","jumlah":0},{"no":11,"kode":"BKP","nama":"Benturan Kepentingan","jumlah":0},{"no":12,"kode":"WBS","nama":"WBS","jumlah":0},{"no":13,"kode":"TDB1","nama":"Kekerasan Seksual","jumlah":0},{"no":14,"kode":"TDB2","nama":"Perundungan","jumlah":0},{"no":15,"kode":"TDB3","nama":"Intoleransi","jumlah":0}],"pengaduan_masyarakat":[{"group":"Diklat \u0026 PMP","items":[{"kode":"DUM1","nama":"Luring","counts":{"BKP":0,"GRA":0,"SKM1":4,"SKM2":6,"SKM3":4,"SKM4":9,"SKM5":10,"SKM6":6,"SKM7":7,"SKM8":7,"SKM9":7,"TDB1":0,"TDB2":0,"TDB3":0,"WBS":0},"total":60},{"kode":"DUM2","nama":"Daring","counts":{"BKP":0,"GRA":0,"SKM1":0,"SKM2":0,"SKM3":0,"SKM4":0,"SKM5":0,"SKM6":0,"SKM7":0,"SKM8":0,"SKM9":1,"TDB1":0,"TDB2":0,"TDB3":0,"WBS":0},"total":1},{"kode":"DUM3","nama":"Hybrid","counts":{"BKP":0,"GRA":0,"SKM1":0,"SKM2":0,"SKM3":0,"SKM4":0,"SKM5":0,"SKM6":0,"SKM7":0,"SKM8":0,"SKM9":0,"TDB1":0,"TDB2":0,"TDB3":0,"WBS":0},"total":0}]},{"group":"Non Diklat","items":[{"kode":"DUM4","nama":"PKL","counts":{"BKP":0,"GRA":0,"SKM1":0,"SKM2":0,"SKM3":0,"SKM4":0,"SKM5":0,"SKM6":0,"SKM7":0,"SKM8":0,"SKM9":0,"TDB1":0,"TDB2":0,"TDB3":0,"WBS":0},"total":0},{"kode":"DUM5","nama":"PNBP","counts":{"BKP":0,"GRA":0,"SKM1":0,"SKM2":0,"SKM3":0,"SKM4":0,"SKM5":0,"SKM6":0,"SKM7":0,"SKM8":0,"SKM9":0,"TDB1":0,"TDB2":0,"TDB3":0,"WBS":0},"total":0},{"kode":"DUM6","nama":"Kunjungan","counts":{"BKP":0,"GRA":0,"SKM1":0,"SKM2":0,"SKM3":0,"SKM4":0,"SKM5":0,"SKM6":0,"SKM7":0,"SKM8":0,"SKM9":0,"TDB1":0,"TDB2":0,"TDB3":0,"WBS":0},"total":0}]}],"tindak_lanjut":[{"kode":"SKM1","sudah":0,"belum":4},{"kode":"SKM2","sudah":0,"belum":6},{"kode":"SKM3","sudah":0,"belum":4},{"kode":"SKM4","sudah":0,"belum":9},{"kode":"SKM5","sudah":0,"belum":10},{"kode":"SKM6","sudah":0,"belum":6},{"kode":"SKM7","sudah":0,"belum":7},{"kode":"SKM8","sudah":0,"belum":7},{"kode":"SKM9","sudah":0,"belum":7},{"kode":"GRA","sudah":0,"belum":0},{"kode":"BKP","sudah":0,"belum":0},{"kode":"WBS","sudah":0,"belum":0},{"kode":"TDB1","sudah":0,"belum":0},{"kode":"TDB2","sudah":0,"belum":0},{"kode":"TDB3","sudah":0,"belum":0}]}}